<item id="152" name="school-closed-thanksgiving" parent="151" title="School Closed-Thanksgiving" zoneName="" templateKey="News" state="32" created="08/20/2012 23:38:03" updated="10/15/2014 23:51:07" published="11/22/2012 07:00:00" expires="11/23/2012 07:00:00" sortOrder="670" url="/ContentPages/Index?n2page=152" visible="False" savedBy="admin" typeName="" discriminator="ContentPage" versionIndex="0" ancestralTrail="/5/115/116/151/" alteredPermissions="15" childState="2"><details><detail name="Author" typeName="System.String, mscorlib" meta="" /><detail name="Keywords" typeName="System.String, mscorlib" meta="" /><detail name="Description" typeName="System.String, mscorlib" meta="" /><detail name="SeoTitle" typeName="System.String, mscorlib" meta="" /><detail name="Text" typeName="System.String, mscorlib" meta="" /></details><detailCollections><collection name="AuthorizedRoles_Write"><detail name="AuthorizedRoles_Write" typeName="System.String, mscorlib" meta="" encoded="True"><![CDATA[Writers]]></detail><detail name="AuthorizedRoles_Write" typeName="System.String, mscorlib" meta="" encoded="True"><![CDATA[Editors]]></detail><detail name="AuthorizedRoles_Write" typeName="System.String, mscorlib" meta="" encoded="True"><![CDATA[Administrators]]></detail></collection><collection name="AuthorizedRoles_Publish"><detail name="AuthorizedRoles_Publish" typeName="System.String, mscorlib" meta="" encoded="True"><![CDATA[Writers]]></detail><detail name="AuthorizedRoles_Publish" typeName="System.String, mscorlib" meta="" encoded="True"><![CDATA[Editors]]></detail><detail name="AuthorizedRoles_Publish" typeName="System.String, mscorlib" meta="" encoded="True"><![CDATA[Administrators]]></detail></collection><collection name="AuthorizedRoles_Administer"><detail name="AuthorizedRoles_Administer" typeName="System.String, mscorlib" meta="" encoded="True"><![CDATA[Writers]]></detail><detail name="AuthorizedRoles_Administer" typeName="System.String, mscorlib" meta="" encoded="True"><![CDATA[Editors]]></detail><detail name="AuthorizedRoles_Administer" typeName="System.String, mscorlib" meta="" encoded="True"><![CDATA[Administrators]]></detail></collection></detailCollections><children /><authorizations><role>Everyone</role><role>Members</role><role>Writers</role><role>Editors</role><role>Administrators</role></authorizations><properties><property name="Summary" typeName="System.String, mscorlib"><![CDATA[]]></property><property name="Image" typeName="System.String, mscorlib"><![CDATA[]]></property></properties></item>