<item id="89" name="lots-of-upcoming-october-events" parent="78" title="Lots of upcoming October events:" zoneName="" templateKey="News" state="16" created="10/03/2013 14:46:46" updated="10/15/2014 23:50:01" published="10/03/2013 14:40:52" expires="" sortOrder="-505" url="/ContentPages/Index?n2page=89" visible="False" savedBy="admin" typeName="" discriminator="ContentPage" versionIndex="1" ancestralTrail="/5/16/72/78/" alteredPermissions="0" childState="2"><details><detail name="SeoTitle" typeName="System.String, mscorlib" meta="" /><detail name="Text" typeName="System.String, mscorlib" meta="" encoded="True"><![CDATA[&lt;ul&gt;
	&lt;li&gt;Come join us at the Parent Academy/PTO meeting on 10/16 in the LCS Library.&lt;/li&gt;
	&lt;li&gt;Don&amp;#39;t forget school picture day on 10/17.&lt;/li&gt;
	&lt;li&gt;Teacher Conferences 10/22 through&amp;nbsp;10/25 - &lt;strong&gt;EARLY DISMISSAL AT 12:45&lt;/strong&gt;.&lt;/li&gt;
	&lt;li&gt;Battle of the Books Kick-offs 10/22 &amp;amp; 10/23 (please see flyers and forms for details and&amp;nbsp;signup info).&lt;/li&gt;
	&lt;li&gt;Trial of the Big Bad Wolf Kick-off (flyer to be coming shortly).&lt;/li&gt;
	&lt;li&gt;Halloween Festivity 10/25 (details to be coming shortly).&lt;/li&gt;
&lt;/ul&gt;

&lt;p&gt;&amp;nbsp;&lt;/p&gt;

&lt;p&gt;&amp;nbsp;&lt;/p&gt;
]]></detail></details><detailCollections /><children /><authorizations /><properties><property name="Summary" typeName="System.String, mscorlib"><![CDATA[
	Come join us at the Parent Academy/PTO meeting on 10/16 in the LCS Library.
	Don&#39;t forget school picture day on 10/17.
	Teacher Conferences 10/22 through&nbsp;10/25 - EARLY DISMISSAL AT 12:45.]]></property><property name="Image" typeName="System.String, mscorlib"><![CDATA[]]></property></properties></item>